models_items/__init__.py
models_items/items.py
models_items/models.py
models_items-0.1.0.dist-info/LICENSE.txt
models_items-0.1.0.dist-info/METADATA
models_items-0.1.0.dist-info/WHEEL
models_items-0.1.0.dist-info/top_level.txt
models_items-0.1.0.dist-info/RECORD
