Metadata-Version: 2.1
Name: models-items
Version: 0.1.0
Summary: Models and Items files for the Scrape & Dash project.
Home-page: https://github.com/justinandronicos/models_items
Author: Justin Andronicos
License: UNKNOWN
Platform: UNKNOWN
Classifier: Programming Language :: Python :: 3
Classifier: License :: OSI Approved :: MIT License
Classifier: Operating System :: OS Independent
Requires-Python: >=3.8
License-File: LICENSE.txt
